edgar_analytics/__init__.py
edgar_analytics/cli.py
edgar_analytics/config.py
edgar_analytics/data_utils.py
edgar_analytics/forecasting.py
edgar_analytics/layout_strategy.py
edgar_analytics/logging_utils.py
edgar_analytics/metrics.py
edgar_analytics/multi_period_analysis.py
edgar_analytics/orchestrator.py
edgar_analytics/panel_layout.py
edgar_analytics/reporting.py
edgar_analytics/synonyms.py
edgar_analytics/synonyms_utils.py
tests/__init__.py
tests/conftest.py
tests/test_cli.py
tests/test_data_utils.py
tests/test_forecasting.py
tests/test_metrics.py
tests/test_multi_period_analysis.py
tests/test_orchestrator.py
tests/test_reporting.py
tests/test_synonyms_utils.py
edgar_analytics-0.1.5.dist-info/LICENSE
edgar_analytics-0.1.5.dist-info/METADATA
edgar_analytics-0.1.5.dist-info/WHEEL
edgar_analytics-0.1.5.dist-info/entry_points.txt
edgar_analytics-0.1.5.dist-info/top_level.txt
edgar_analytics-0.1.5.dist-info/RECORD
